{
  "connected": [
    {
      "name": "Slack",
      "status": "connected",
      "description": "Bot and app tokens valid. groupPolicy=open (security warning noted).",
      "lastVerified": "2026-03-20T11:46:00Z"
    },
    {
      "name": "GitHub",
      "status": "connected",
      "description": "Logged in as nickxma via keyring. Scopes: admin:public_key, gist, read:org, repo.",
      "lastVerified": "2026-03-20T11:46:00Z"
    },
    {
      "name": "Obsidian",
      "status": "connected",
      "description": "obsidian-cli installed. Vault at ~/Obsidian with 5+ top-level folders.",
      "lastVerified": "2026-03-20T11:46:00Z"
    },
    {
      "name": "Google Calendar",
      "status": "connected",
      "description": "OAuth credentials present for nickxma@gmail.com. Calendar listing works.",
      "lastVerified": "2026-03-20T11:46:00Z"
    },
    {
      "name": "Tailscale",
      "status": "connected",
      "description": "Active on mmm4. 8 nodes in tailnet (3 online: mmm4, iphone181, n1, n2).",
      "lastVerified": "2026-03-20T11:46:00Z"
    },
    {
      "name": "Paperclip",
      "status": "connected",
      "description": "Running v2026.318.0. Local trusted deployment, auth ready.",
      "lastVerified": "2026-03-20T11:46:00Z"
    },
    {
      "name": "Things 3",
      "status": "connected",
      "description": "things CLI installed at /opt/homebrew/bin/things.",
      "lastVerified": "2026-03-20T11:46:00Z"
    },
    {
      "name": "1Password",
      "status": "connected",
      "description": "op CLI installed at /opt/homebrew/bin/op.",
      "lastVerified": "2026-03-20T11:46:00Z"
    }
  ],
  "attention": [
    {
      "name": "Google Workspace",
      "status": "partial",
      "description": "gog credentials exist for nickxma@gmail.com but config.json missing. OAuth auth only, no service account.",
      "lastVerified": "2026-03-20T11:46:00Z"
    }
  ],
  "available": [
    {
      "name": "Brave Search",
      "status": "available",
      "description": "web_search tool available via OpenClaw. No local config file found but tool is functional.",
      "lastVerified": "2026-03-20T11:46:00Z"
    }
  ],
  "updatedAt": "2026-03-20T11:46:00Z"
}
